functional_iterators/__init__.py
functional_iterators-2.0.0.dist-info/METADATA
functional_iterators-2.0.0.dist-info/WHEEL
functional_iterators-2.0.0.dist-info/licenses/LICENSE
functional_iterators-2.0.0.dist-info/RECORD
