Metadata-Version: 2.4
Name: functional_iterators
Version: 2.0.0
Summary: rust-style iterating functions (fiterators)
Project-URL: Homepage, https://codeberg.org/Kwonunn/fiterators
Author-email: Vivian <me@vivstuff.gay>
License: # KOMBUCHA LICENSE
License-File: LICENSE
Classifier: Operating System :: OS Independent
Classifier: Programming Language :: Python :: 3
Requires-Python: >=3.10
